ldap3cli.py
ldap3cli-0.1.0.dist-info/DESCRIPTION.rst
ldap3cli-0.1.0.dist-info/METADATA
ldap3cli-0.1.0.dist-info/RECORD
ldap3cli-0.1.0.dist-info/WHEEL
ldap3cli-0.1.0.dist-info/entry_points.txt
ldap3cli-0.1.0.dist-info/metadata.json
ldap3cli-0.1.0.dist-info/top_level.txt
