Metadata-Version: 2.0
Name: ldap3cli
Version: 0.1.0
Summary: Command line utility for accessing LDAP servers, based on ldap3
Home-page: https://github.com/cannatag/ldap3-cli
Author: Giovanni Cannata
Author-email: cannatag@gmail.com
License: LGPL v3
Keywords: python3 python2 ldap
Platform: UNKNOWN
Classifier: Development Status :: 3 - Alpha
Classifier: Environment :: Console
Classifier: Intended Audience :: System Administrators
Classifier: Operating System :: MacOS :: MacOS X
Classifier: Operating System :: Microsoft :: Windows
Classifier: Operating System :: POSIX :: Linux
Classifier: License :: OSI Approved :: GNU Lesser General Public License v3 (LGPLv3)
Classifier: Programming Language :: Python
Classifier: Programming Language :: Python :: 2
Classifier: Programming Language :: Python :: 3
Classifier: Topic :: System :: Systems Administration :: Authentication/Directory :: LDAP
Requires-Dist: click (>=6.7)
Requires-Dist: colorama (>=0.3.7)
Requires-Dist: ldap3 (>=2.2.2)
Requires-Dist: pyasn1 (>=0.2.3)
